coqui_stt_training/GRAPH_VERSION
coqui_stt_training/VERSION
coqui_stt_training/__init__.py
coqui_stt_training/deepspeech_model.py
coqui_stt_training/evaluate.py
coqui_stt_training/evaluate_export.py
coqui_stt_training/evaluate_flashlight.py
coqui_stt_training/evaluate_from_csv.py
coqui_stt_training/evaluate_wav2vec2am.py
coqui_stt_training/export.py
coqui_stt_training/train.py
coqui_stt_training/training_graph_inference.py
coqui_stt_training/training_graph_inference_flashlight.py
coqui_stt_training/transcribe.py
coqui_stt_training/util/__init__.py
coqui_stt_training/util/audio.py
coqui_stt_training/util/augmentations.py
coqui_stt_training/util/auto_input.py
coqui_stt_training/util/check_characters.py
coqui_stt_training/util/checkpoints.py
coqui_stt_training/util/config.py
coqui_stt_training/util/downloader.py
coqui_stt_training/util/evaluate_tools.py
coqui_stt_training/util/feeding.py
coqui_stt_training/util/gpu.py
coqui_stt_training/util/helpers.py
coqui_stt_training/util/importers.py
coqui_stt_training/util/io.py
coqui_stt_training/util/lm_optimize.py
coqui_stt_training/util/lm_optimize_wav2vec2am.py
coqui_stt_training/util/multiprocessing.py
coqui_stt_training/util/sample_collections.py
coqui_stt_training/util/stm.py
coqui_stt_training/util/text.py
coqui_stt_training-1.4.0.dist-info/LICENSE
coqui_stt_training-1.4.0.dist-info/METADATA
coqui_stt_training-1.4.0.dist-info/WHEEL
coqui_stt_training-1.4.0.dist-info/top_level.txt
coqui_stt_training-1.4.0.dist-info/RECORD
